README
setup.py
useless/__init__.py
useless.pipes.egg-info/PKG-INFO
useless.pipes.egg-info/SOURCES.txt
useless.pipes.egg-info/dependency_links.txt
useless.pipes.egg-info/top_level.txt
useless/pipes/__init__.py
useless/pipes/common.py
useless/pipes/fs.py
useless/pipes/pipes.py
useless/pipes/tupleize.py