Metadata-Version: 1.0
Name: useless.pipes
Version: 0.0.1
Summary: Sugar around generators.
Home-page: http://github.com/kaste/useless.pipes
Author: herr kaste
Author-email: herr.kaste@gmail.com
License: UNKNOWN
Platform: UNKNOWN
Classifier: Development Status :: 3 - Alpha
Classifier: Intended Audience :: Developers
Classifier: License :: OSI Approved :: BSD License
Classifier: Operating System :: OS Independent
Classifier: Programming Language :: Python
Classifier: Topic :: Internet :: WWW/HTTP
Classifier: Topic :: Software Development :: Libraries
